survey_bot
