Metadata-Version: 2.1
Name: django-survey-bot
Version: 0.0.1
Summary: A Survey Bot package developed using Django to create Bots and collect leads
Home-page: UNKNOWN
Author: Digitalmesh
Author-email: subish@digitalmesh.com
License: MIT
Platform: UNKNOWN
Classifier: Environment :: Web Environment
Classifier: Framework :: Django
Classifier: Framework :: Django :: 3.2
Classifier: Framework :: Django :: 4.0
Classifier: Intended Audience :: Developers
Classifier: License :: OSI Approved :: BSD License
Classifier: Operating System :: OS Independent
Classifier: Programming Language :: Python
Classifier: Programming Language :: Python :: 3
Classifier: Programming Language :: Python :: 3.8
Classifier: Programming Language :: Python :: 3.9
Classifier: Topic :: Internet :: WWW/HTTP
Classifier: Topic :: Internet :: WWW/HTTP :: Dynamic Content
Requires-Dist: beautifulsoup4
Requires-Dist: djangorestframework
Requires-Dist: redis
